{"basename":"v.hamars.xyz","fileperms":"0755","filetype":"dir","is_writeable":true,"is_readable":true,"is_link":false,"mime":"directory","mtime":1666685742,"path":"","url_path":".","dirsize":45,"files_count":1,"images_count":null,"files":{".user.ini":{"basename":".user.ini","fileperms":"0644","filetype":"file","filesize":45,"is_readable":true,"is_writeable":false,"is_link":false,"mtime":1666672466,"path":".user.ini","ext":"ini","url_path":"./.user.ini"},"css":{"basename":"css","fileperms":"0755","filetype":"dir","filesize":false,"is_readable":true,"is_writeable":true,"is_link":false,"mtime":1666685738,"path":"css","mime":"directory","url_path":"./css"},"js":{"basename":"js","fileperms":"0755","filetype":"dir","filesize":false,"is_readable":true,"is_writeable":true,"is_link":false,"mtime":1666685741,"path":"js","mime":"directory","url_path":"./js"}}}